{
  "project_info": {
    "project_number": "1053675439836",
    "firebase_url": "https://ghousedevdemoapp.firebaseio.com",
    "project_id": "ghousedevdemoapp",
    "storage_bucket": "ghousedevdemoapp.appspot.com"
  },
  "client": [
    {
      "client_info": {
        "mobilesdk_app_id": "1:1053675439836:android:f2d11e812cd0522e155619",
        "android_client_info": {
          "package_name": "dev.ghouse.ghousedevdemoapp"
        }
      },
      "oauth_client": [
        {
          "client_id": "1053675439836-9sdddrntvu49tcloohecvh75elbi05jn.apps.googleusercontent.com",
          "client_type": 3
        }
      ],
      "api_key": [
        {
          "current_key": "AIzaSyCaJThW4ynPeQkQzxidTottIlC4sDttN70"
        }
      ],
      "services": {
        "appinvite_service": {
          "other_platform_oauth_client": [
            {
              "client_id": "1053675439836-9sdddrntvu49tcloohecvh75elbi05jn.apps.googleusercontent.com",
              "client_type": 3
            }
          ]
        }
      }
    }
  ],
  "configuration_version": "1"
}